BODtoJSON/BODtoJSON.py
BODtoJSON/__init_.py
BODtoJSON-0.0.7.dist-info/LICENSE
BODtoJSON-0.0.7.dist-info/LICENSE.txt
BODtoJSON-0.0.7.dist-info/METADATA
BODtoJSON-0.0.7.dist-info/WHEEL
BODtoJSON-0.0.7.dist-info/top_level.txt
BODtoJSON-0.0.7.dist-info/RECORD
