Metadata-Version: 2.1
Name: BODtoJSON
Version: 0.0.7
Summary: Converts Infor QAGIS BODs to  flattened JSON
Home-page: https://github.com/thekakodkar/Mapper
Author: Niraj Kakodkar
Author-email: niraj.kakodkar@gmail.com
License: MIT
Platform: UNKNOWN
Classifier: Programming Language :: Python :: 3
Classifier: License :: OSI Approved :: MIT License
Classifier: Operating System :: OS Independent
Requires-Python: >=3.0
Requires-Dist: xmltodict
